Metadata-Version: 2.1
Name: wxPyGameVideoPlayer
Version: 0.1.8
Summary: Just a simple video player using wxPython, PyGame, and OpenCV
Home-page: http://pypi.python.org/pypi/wxpygamevideoplayer/
Author: David N. Mashburn
Author-email: david.n.mashburn@gmail.com
License: LICENSE.txt
Platform: UNKNOWN
